collectionpy/__init__.py
collectionpy/validate.py
collectionpy/chart/__init__.py
collectionpy/chart/apexcharts.py
collectionpy/chart/googlecharts.py
collectionpy/date/__init__.py
collectionpy/date/dtget.py
collectionpy/date/dtmath.py
collectionpy/math/__init__.py
collectionpy/math/statistic.py
collectionpy/text/__init__.py
collectionpy/text/number.py
collectionpy-1.3.0.dist-info/METADATA
collectionpy-1.3.0.dist-info/WHEEL
collectionpy-1.3.0.dist-info/top_level.txt
collectionpy-1.3.0.dist-info/RECORD
