Metadata-Version: 2.1
Name: collectionpy
Version: 1.3.0
Summary: "collectionpy" is more than just a library; it is a comprehensive tool that provides efficient solutions for various areas, ranging from date manipulation and text formatting to the creation of impressive graphics.
Requires-Dist: numpy
